deepconf/__init__.py
deepconf/outputs.py
deepconf/processors.py
deepconf/utils.py
deepconf/wrapper.py
deepconf-0.1.0.dist-info/METADATA
deepconf-0.1.0.dist-info/WHEEL
deepconf-0.1.0.dist-info/top_level.txt
deepconf-0.1.0.dist-info/RECORD
