Metadata-Version: 2.4
Name: deepconf
Version: 0.1.0
Summary: Enhanced LLM wrapper with DeepConf capabilities
Author: Yichao
Author-email: fuyichao2000@gmail.com
Dynamic: author
Dynamic: author-email
Dynamic: summary
